pinet.py
pinet-0.2.4.dist-info/LICENSE.txt
pinet-0.2.4.dist-info/METADATA
pinet-0.2.4.dist-info/WHEEL
pinet-0.2.4.dist-info/top_level.txt
pinet-0.2.4.dist-info/RECORD
