Metadata-Version: 2.1
Name: pinet
Version: 0.2.4
Summary: Translate Python Code to HTML
Home-page: UNKNOWN
Author: ineerajrajeev
Author-email: neerajshetkar@gmail.com
License: GNU General Public License
Keywords: html,web,piNet,translate
Platform: UNKNOWN
License-File: LICENSE.txt
